cd_mail/__init__.py
cd_mail/read_imap.py
cd_mail/send_smtp.py
cd_mail/version.py
cd_email-0.0.1.dist-info/LICENSE.md
cd_email-0.0.1.dist-info/LICENSE.txt
cd_email-0.0.1.dist-info/METADATA
cd_email-0.0.1.dist-info/WHEEL
cd_email-0.0.1.dist-info/top_level.txt
cd_email-0.0.1.dist-info/RECORD
